yduie/__init__.py
yduie/uie_predict.py
yduie/utils/__init__.py
yduie/utils/downloader.py
yduie-1.5.dist-info/METADATA
yduie-1.5.dist-info/WHEEL
yduie-1.5.dist-info/top_level.txt
yduie-1.5.dist-info/RECORD
