Metadata-Version: 2.1
Name: yduie
Version: 1.5
Summary: 影刀信息抽取
Home-page: https://github.com/mingo-doer/uie
Author: jiaer
Author-email: jia.er@winrobot360.com
License: Apache 2.0
Classifier: Development Status :: 4 - Beta
Classifier: Operating System :: OS Independent
Classifier: Intended Audience :: Developers
Classifier: License :: OSI Approved :: Apache Software License
Classifier: Programming Language :: Python :: 3
Classifier: Topic :: Scientific/Engineering :: Artificial Intelligence
Requires-Dist: onnxruntime
Requires-Dist: numpy
Requires-Dist: six
Requires-Dist: requests
